{
   "patternFamillies": [
      {
         "patternFamillyName": "Creational",
         "patterns": [
            {
               "patternName": "Singleton",
               "patternFilesDirectory": "creational_patterns/singleton",
               "files": [
                  {
                     "defaultName": "Singleton.java",
                     "sourceFile": "Singleton.java"
                     
                  }
               ],
               "params": {
                  "textFieldParams": [
                     {
                        "shouldBeVisible": true,
                        "label": "Singleton class name",
                        "defaultValue": "Singleton",
                        "replace": "$CLASSNAME$",
                        "filename": ""
                     },
                     {
                        "shouldBeVisible": true,
                        "label": "Name of an Singleton instance",
                        "defaultValue": "INSTANCE",
                        "replace": "$INSTANCENAME$",
                        "filename": ""
                     }
                  ],
                  "selectParams": []
               }
            },
            {
               "patternName": "Builder",
               "patternFilesDirectory": "creational_patterns/builder",
               "files": [
                  {
                     "defaultName": "Builder.java",
                     "sourceFile": "Builder.java"
                  },
                  {
                     "defaultName": "Director.java",
                     "sourceFile": "Director.java"
                  },
                  {
                     "defaultName": "ConcreteBuilder.java",
                     "sourceFile": "ConcreteBuilder.java"
                  },
                  {
                     "defaultName": "Product.java",
                     "sourceFile": "Product.java"
                  }
               ],
               "params": {
                  "textFieldParams": [
                     {
                        "shouldBeVisible": true,
                        "label": "Builder class name",
                        "defaultValue": "Builder",
                        "replace": "$BUILDER_CLASSNAME$",
                        "filename": ""
                     },
                     {
                        "shouldBeVisible": true,
                        "label": "Builder methods",
                        "defaultValue": "void buildPartA();\nvoid buildPartB();",
                        "replace": "$BUILDER_METHODS$",
                        "filename": ""
                     },
                     {
                        "shouldBeVisible": false,
                        "label": "Builder methods extended",
                        "defaultValue": "$BUILDER_METHODS$",
                        "replace": "$BUILDER_METHODS_EXTENDED$",
                        "filename": ""
                     },
                     {
                        "shouldBeVisible": true,
                        "label": "Director class name",
                        "defaultValue": "Director",
                        "replace": "$DIRECTOR_CLASSNAME$",
                        "filename": ""
                     },
                     {
                        "shouldBeVisible": true,
                        "label": "Product class name",
                        "defaultValue": "Product",
                        "replace": "$PRODUCT_CLASSNAME$",
                        "filename": ""
                     },
                     {
                        "shouldBeVisible": true,
                        "label": "Concrete Builder class name",
                        "defaultValue": "ConcreteBuilder",
                        "replace": "$CONCRETE_BUILDER_CLASSNAME1$",
                        "filename": "ConcreteBuilder.java"
                     }
                  ],

                  "selectParams": [
                     {
                        "label": "Number of ConcreteBuilder classes",
                        "fileNameToBeMultiplied": "ConcreteBuilder.java",
                        "minNumber": 1,
                        "maxNumber": 5
                     }
                  ]
               }
            },
            {
               "patternName": "Factory Method",
               "patternFilesDirectory": "creational_patterns/factorymethod",
               "files": [
                  {
                     "defaultName": "Creator.java",
                     "sourceFile": "Creator.java"
                  },
                  {
                     "defaultName": "ConcreteCreator.java",
                     "sourceFile": "ConcreteCreator.java"
                  },
                  {
                     "defaultName": "Product.java",
                     "sourceFile": "Product.java"
                  },
                  {
                     "defaultName": "ConcreteProduct.java",
                     "sourceFile": "ConcreteProduct.java"
                  }
               ],
               "params": {
                  "textFieldParams": [],
                  "selectParams": []
               }
            },
            {
               "patternName": "Abstract Factory",
               "patternFilesDirectory": "creational_patterns/abstractfactory",
               "files": [
                  {
                     "defaultName": "Client.java",
                     "sourceFile": "Client.java"
                  },
                  {
                     "defaultName": "AbstractFactory.java",
                     "sourceFile": "AbstractFactory.java"
                  },
                  {
                     "defaultName": "ConcreteFactory1.java",
                     "sourceFile": "ConcreteFactory1.java"
                  },
                  {
                     "defaultName": "ConcreteFactory2.java",
                     "sourceFile": "ConcreteFactory2.java"
                  },
                  {
                     "defaultName": "AbstractProductA.java",
                     "sourceFile": "AbstractProductA.java"
                  },
                  {
                     "defaultName": "AbstractProductB.java",
                     "sourceFile": "AbstractProductB.java"
                  },
                  {
                     "defaultName": "ConcreteProductA.java",
                     "sourceFile": "ConcreteProductA.java"
                  },
                  {
                     "defaultName": "ConcreteProductB.java",
                     "sourceFile": "ConcreteProductB.java"
                  }
               ],
               "params": {
                  "textFieldParams": [],
                  "selectParams": []
               }
            },
            {
               "patternName": "Prototype",
               "patternFilesDirectory": "creational_patterns/prototype",
               "files": [
                  {
                     "defaultName": "Client.java",
                     "sourceFile": "Client.java"
                  },
                  {
                     "defaultName": "Prototype.java",
                     "sourceFile": "Prototype.java"
                  },
                  {
                     "defaultName": "ConcretePrototype.java",
                     "sourceFile": "ConcretePrototype.java"
                  }
               ],
               "params": {
                  "textFieldParams": [],
                  "selectParams": []
               }
            }
         ]
      },
      {
         "patternFamillyName": "Structural",
         "patterns": [
            {
               "patternName": "Adapter",
               "patternFilesDirectory": "",
               "files": [],
               "params": {
                  "textFieldParams": [],
                  "selectParams": []
               }
            },
            {
               "patternName": "Bridge",
               "patternFilesDirectory": "",
               "files": [],
               "params": {
                  "textFieldParams": [],
                  "selectParams": []
               }
            },
            {
               "patternName": "Composite",
               "patternFilesDirectory": "",
               "files": [],
               "params": {
                  "textFieldParams": [],
                  "selectParams": []
               }
            },
            {
               "patternName": "Decorator",
               "patternFilesDirectory": "",
               "files": [],
               "params": {
                  "textFieldParams": [],
                  "selectParams": []
               }
            },
            {
               "patternName": "Facade",
               "patternFilesDirectory": "",
               "files": [],
               "params": {
                  "textFieldParams": [],
                  "selectParams": []
               }
            },
            {
               "patternName": "Flyweight",
               "patternFilesDirectory": "",
               "files": [],
               "params": {
                  "textFieldParams": [],
                  "selectParams": []
               }
            },
            {
               "patternName": "Proxy",
               "patternFilesDirectory": "",
               "files": [],
               "params": {
                  "textFieldParams": [],
                  "selectParams": []
               }
            }
         ]
      },
      {
         "patternFamillyName": "Behavioral",
         "patterns": [
            {
               "patternName": "Chain of responsibility",
               "patternFilesDirectory": "",
               "files": [],
               "params": {
                  "textFieldParams": [],
                  "selectParams": []
               }
            },
            {
               "patternName": "Command",
               "patternFilesDirectory": "",
               "files": [],
               "params": {
                  "textFieldParams": [],
                  "selectParams": []
               }
            },
            {
               "patternName": "Iterator",
               "patternFilesDirectory": "",
               "files": [],
               "params": {
                  "textFieldParams": [],
                  "selectParams": []
               }
            },
            {
               "patternName": "Mediator",
               "patternFilesDirectory": "",
               "files": [],
               "params": {
                  "textFieldParams": [],
                  "selectParams": []
               }
            },
            {
               "patternName": "Memento",
               "patternFilesDirectory": "",
               "files": [],
               "params": {
                  "textFieldParams": [],
                  "selectParams": []
               }
            },
            {
               "patternName": "Observer",
               "patternFilesDirectory": "",
               "files": [],
               "params": {
                  "textFieldParams": [],
                  "selectParams": []
               }
            },
            {
               "patternName": "State",
               "patternFilesDirectory": "",
               "files": [],
               "params": {
                  "textFieldParams": [],
                  "selectParams": []
               }
            },
            {
               "patternName": "Strategy",
               "patternFilesDirectory": "",
               "files": [],
               "params": {
                  "textFieldParams": [],
                  "selectParams": []
               }
            },
            {
               "patternName": "Template Method",
               "patternFilesDirectory": "",
               "files": [],
               "params": {
                  "textFieldParams": [],
                  "selectParams": []
               }
            },
            {
               "patternName": "Visitor",
               "patternFilesDirectory": "",
               "files": [],
               "params": {
                  "textFieldParams": [],
                  "selectParams": []
               }
            }
         ]
      }
   ]
}